tardigrade/__init__.py
tardigrade/ids/__init__.py
tardigrade/ids/ids.py
tardigrade/ids/kitsune/__init__.py
tardigrade/ids/kitsune/kitsune.py
tardigrade/ids/kitsune/kitsune_ids/__init__.py
tardigrade/ids/kitsune/kitsune_ids/feature_squeeze.py
tardigrade/ids/kitsune/kitsune_ids/kitsune.py
tardigrade/ids/kitsune/kitsune_ids/parse_with_kitsune.py
tardigrade/ids/kitsune/kitsune_ids/KitNET/KitNET.py
tardigrade/ids/kitsune/kitsune_ids/KitNET/__init__.py
tardigrade/ids/kitsune/kitsune_ids/KitNET/corClust.py
tardigrade/ids/kitsune/kitsune_ids/KitNET/dA.py
tardigrade/ids/kitsune/kitsune_ids/KitNET/utils.py
tardigrade/utils/__init__.py
tardigrade/utils/metrics.py
tarda-0.0.10.dist-info/LICENSE
tarda-0.0.10.dist-info/METADATA
tarda-0.0.10.dist-info/WHEEL
tarda-0.0.10.dist-info/top_level.txt
tarda-0.0.10.dist-info/RECORD
