Metadata-Version: 2.1
Name: tarda
Version: 0.0.10
Summary: A library for collection of IDS & robust-IDS and tools for evaluating them
Home-page: https://github.com/spg-iitd/tardigrade
Author: Ravi Ranjan Singh
Author-email: raviranjans821@gmail.com
License: MIT
Keywords: ids adversarial network nids
License-File: LICENSE
Requires-Dist: scapy
Requires-Dist: numpy
Requires-Dist: pandas
Requires-Dist: matplotlib
Requires-Dist: scikit-learn
Requires-Dist: scipy
Requires-Dist: tqdm
Requires-Dist: torch
Requires-Dist: torchvision
Requires-Dist: torchsummary
Requires-Dist: torchattacks
